isogeotoxlsx/__about__.py
isogeotoxlsx/__init__.py
isogeotoxlsx/isogeo2xlsx.py
isogeotoxlsx/isogeoFromxlsx.py
isogeotoxlsx/i18n/__init__.py
isogeotoxlsx/i18n/english.py
isogeotoxlsx/i18n/french.py
isogeotoxlsx/matrix/__init__.py
isogeotoxlsx/matrix/attributes.py
isogeotoxlsx/matrix/raster.py
isogeotoxlsx/matrix/resource.py
isogeotoxlsx/matrix/service.py
isogeotoxlsx/matrix/vector.py
isogeotoxlsx/utils/__init__.py
isogeotoxlsx/utils/formatter.py
isogeotoxlsx/utils/stats.py
isogeo_export_xl-1.3.2.dist-info/LICENSE
isogeo_export_xl-1.3.2.dist-info/METADATA
isogeo_export_xl-1.3.2.dist-info/WHEEL
isogeo_export_xl-1.3.2.dist-info/top_level.txt
isogeo_export_xl-1.3.2.dist-info/RECORD
