Metadata-Version: 2.1
Name: isogeo-export-xl
Version: 1.3.2
Summary: Toolbelt to export metadata from the Isogeo REST API into Microsoft Excel workbooks (.xlsx).
Home-page: https://github.com/isogeo/export-xlsx-py/
Author: Isogeo
Author-email: contact@isogeo.com
License: LGPL3
Project-URL: Docs, https://isogeo-export-xlsx-py.readthedocs.io/
Project-URL: Bug Reports, https://github.com/isogeo/export-xlsx-py/issues/
Project-URL: Source, https://github.com/isogeo/export-xlsx-py/
Keywords: GIS metadata INSPIRE Isogeo API REST geographical data ISO19139 XLSX Excel
Platform: UNKNOWN
Classifier: Intended Audience :: Developers
Classifier: Intended Audience :: Information Technology
Classifier: Programming Language :: Python :: 3
Classifier: Programming Language :: Python :: 3.6
Classifier: Programming Language :: Python :: 3.7
Classifier: Development Status :: 5 - Production/Stable
Classifier: License :: OSI Approved :: GNU General Public License v3 (GPLv3)
Classifier: Operating System :: OS Independent
Classifier: Topic :: Software Development :: Libraries :: Python Modules
Requires-Python: >=3.6, <4
Requires-Dist: isogeo-pysdk (<=3.5,>=3.3)
Requires-Dist: openpyxl (==3.0.*)
Provides-Extra: dev
Requires-Dist: black ; extra == 'dev'
Requires-Dist: python-dotenv ; extra == 'dev'
Provides-Extra: test
Requires-Dist: pytest ; extra == 'test'
Requires-Dist: pytest-cov ; extra == 'test'
